libwwz/__init__.py
libwwz/plot_methods.py
libwwz/wwz.py
libwwz-1.3.4.dist-info/LICENSE
libwwz-1.3.4.dist-info/METADATA
libwwz-1.3.4.dist-info/WHEEL
libwwz-1.3.4.dist-info/top_level.txt
libwwz-1.3.4.dist-info/RECORD
