Metadata-Version: 2.1
Name: libwwz
Version: 1.3.4
Summary: Library for computing the weighted wavelet Z transform.
Author-email: "RedVox, Inc" <support@redvox.io>
License: 
Project-URL: homepage, https://github.com/RedVoxInc/libwwz
Project-URL: PyPI, https://pypi.org/project/libwwz/
Requires-Python: >=3.8
License-File: LICENSE
Requires-Dist: joblib ==1.4.2
Requires-Dist: matplotlib ==3.9.2
Requires-Dist: numpy ==1.26.4
